[
  {
    "url": "http://localhost:3000/api/users",
    "method": "GET",
    "resource": "users"
  },
  {
    "url": "http://localhost:3000/api/users",
    "method": "POST",
    "resource": "users"
  },
  {
    "url": "http://localhost:3000/api/users/123",
    "method": "GET",
    "resource": "users"
  },
  {
    "url": "http://localhost:3000/api/users/123",
    "method": "PUT",
    "resource": "users"
  },
  {
    "url": "http://localhost:3000/api/users/123",
    "method": "DELETE",
    "resource": "users"
  },
  {
    "url": "http://localhost:3000/api/orders",
    "method": "GET",
    "resource": "orders"
  },
  {
    "url": "http://localhost:3000/api/orders",
    "method": "POST",
    "resource": "orders"
  }
]
